[
  {
    "date": "2025-01-01",
    "name": "New Year's Day"
  },
  {
    "date": "2025-02-16",
    "name": "Day of Restoration of the State of Lithuania"
  },
  {
    "date": "2025-03-11",
    "name": "Day of Restoration of Independence of Lithuania"
  },
  {
    "date": "2025-04-20",
    "name": "Easter Sunday"
  },
  {
    "date": "2025-04-21",
    "name": "Easter Monday"
  },
  {
    "date": "2025-05-01",
    "name": "International Workers' Day"
  },
  {
    "date": "2025-05-04",
    "name": "Mother's Day"
  },
  {
    "date": "2025-06-01",
    "name": "Father's Day"
  },
  {
    "date": "2025-06-24",
    "name": "Day of Dew and Saint John"
  },
  {
    "date": "2025-07-06",
    "name": "Statehood Day"
  },
  {
    "date": "2025-08-15",
    "name": "Assumption Day"
  },
  {
    "date": "2025-11-01",
    "name": "All Saints' Day"
  },
  {
    "date": "2025-11-02",
    "name": "All Souls' Day"
  },
  {
    "date": "2025-12-24",
    "name": "Christmas Eve"
  },
  {
    "date": "2025-12-25",
    "name": "Christmas Day"
  },
  {
    "date": "2025-12-26",
    "name": "Second Day of Christmas"
  }
]