[
  {
    "date": "2025-01-01",
    "name": "New Year's Day"
  },
  {
    "date": "2025-03-01",
    "name": "Nuclear Victims Remembrance Day"
  },
  {
    "date": "2025-04-18",
    "name": "Good Friday"
  },
  {
    "date": "2025-05-01",
    "name": "Constitution Day"
  },
  {
    "date": "2025-07-04",
    "name": "Fisherman's Day"
  },
  {
    "date": "2025-09-05",
    "name": "Dri-jerbal Day"
  },
  {
    "date": "2025-09-26",
    "name": "Manit Day"
  },
  {
    "date": "2025-11-17",
    "name": "President's Day"
  },
  {
    "date": "2025-12-05",
    "name": "Gospel Day"
  },
  {
    "date": "2025-12-25",
    "name": "Christmas Day"
  }
]