{
  "2026-01-01": "New Year's Day",
  "2026-02-16": "Day of Restoration of the State of Lithuania",
  "2026-03-11": "Day of Restoration of Independence of Lithuania",
  "2026-04-05": "Easter Sunday",
  "2026-04-06": "Easter Monday",
  "2026-05-01": "International Workers' Day",
  "2026-05-03": "Mother's Day",
  "2026-06-07": "Father's Day",
  "2026-06-24": "Day of Dew and Saint John",
  "2026-07-06": "Statehood Day",
  "2026-08-15": "Assumption Day",
  "2026-11-01": "All Saints' Day",
  "2026-11-02": "All Souls' Day",
  "2026-12-24": "Christmas Eve",
  "2026-12-25": "Christmas Day",
  "2026-12-26": "Second Day of Christmas",
  "2027-01-01": "New Year's Day",
  "2027-02-16": "Day of Restoration of the State of Lithuania",
  "2027-03-11": "Day of Restoration of Independence of Lithuania",
  "2027-03-28": "Easter Sunday",
  "2027-03-29": "Easter Monday",
  "2027-05-01": "International Workers' Day",
  "2027-05-02": "Mother's Day",
  "2027-06-06": "Father's Day",
  "2027-06-24": "Day of Dew and Saint John",
  "2027-07-06": "Statehood Day",
  "2027-08-15": "Assumption Day",
  "2027-11-01": "All Saints' Day",
  "2027-11-02": "All Souls' Day",
  "2027-12-24": "Christmas Eve",
  "2027-12-25": "Christmas Day",
  "2027-12-26": "Second Day of Christmas"
}