{
  "2026-01-01": "New Year's Day",
  "2026-02-10": "Feast of Saint Paul's Shipwreck",
  "2026-03-19": "Feast of Saint Joseph",
  "2026-03-31": "Freedom Day",
  "2026-04-03": "Good Friday",
  "2026-05-01": "Worker's Day",
  "2026-06-07": "Sette Giugno",
  "2026-06-29": "Feast of Saint Peter and Saint Paul",
  "2026-08-15": "Feast of the Assumption",
  "2026-09-08": "Feast of Our Lady of Victories",
  "2026-09-21": "Independence Day",
  "2026-12-08": "Feast of the Immaculate Conception",
  "2026-12-13": "Republic Day",
  "2026-12-25": "Christmas Day",
  "2027-01-01": "New Year's Day",
  "2027-02-10": "Feast of Saint Paul's Shipwreck",
  "2027-03-19": "Feast of Saint Joseph",
  "2027-03-31": "Freedom Day",
  "2027-03-26": "Good Friday",
  "2027-05-01": "Worker's Day",
  "2027-06-07": "Sette Giugno",
  "2027-06-29": "Feast of Saint Peter and Saint Paul",
  "2027-08-15": "Feast of the Assumption",
  "2027-09-08": "Feast of Our Lady of Victories",
  "2027-09-21": "Independence Day",
  "2027-12-08": "Feast of the Immaculate Conception",
  "2027-12-13": "Republic Day",
  "2027-12-25": "Christmas Day"
}